numberwang.py
numberwang-0.0.2.dist-info/DESCRIPTION.rst
numberwang-0.0.2.dist-info/METADATA
numberwang-0.0.2.dist-info/RECORD
numberwang-0.0.2.dist-info/WHEEL
numberwang-0.0.2.dist-info/entry_points.txt
numberwang-0.0.2.dist-info/metadata.json
numberwang-0.0.2.dist-info/top_level.txt
