Metadata-Version: 2.0
Name: numberwang
Version: 0.0.2
Summary: A module / utility to determine if something is numberwang.
Home-page: https://github.com/ntoll/numberwang
Author: Nicholas H.Tollervey
Author-email: ntoll@ntoll.org
License: MIT
Platform: UNKNOWN
Classifier: Development Status :: 4 - Beta
Classifier: Environment :: Console
Classifier: Intended Audience :: Developers
Classifier: Intended Audience :: Education
Classifier: License :: OSI Approved :: MIT License
Classifier: Operating System :: POSIX
Classifier: Operating System :: Microsoft :: Windows
Classifier: Programming Language :: Python :: 3.5
Classifier: Programming Language :: Python :: 3.6
Classifier: Topic :: Education
